MANIFEST.in
README.rst
setup.cfg
setup.py
subp/__init__.py
subp/core.py
subp.egg-info/PKG-INFO
subp.egg-info/SOURCES.txt
subp.egg-info/dependency_links.txt
subp.egg-info/top_level.txt
tests/test.py